technove/__init__.py
technove/exceptions.py
technove/models.py
technove/technove.py
python_technove-2.0.0.dist-info/LICENSE
python_technove-2.0.0.dist-info/METADATA
python_technove-2.0.0.dist-info/WHEEL
python_technove-2.0.0.dist-info/RECORD
