Metadata-Version: 2.3
Name: python-technove
Version: 2.0.0
Summary: Asynchronous Python client for TechnoVE.
License: MIT
Keywords: TechnoVE,EV,Charger,client
Author: Christophe Gagnier
Author-email: christopheextensions@gmail.com
Maintainer: Christophe Gagnier
Maintainer-email: christopheextensions@gmail.com
Requires-Python: >=3.11,<4.0
Classifier: Development Status :: 4 - Beta
Classifier: Framework :: AsyncIO
Classifier: Intended Audience :: Developers
Classifier: License :: OSI Approved :: MIT License
Classifier: Natural Language :: English
Classifier: Programming Language :: Python :: 3
Classifier: Programming Language :: Python :: 3.11
Classifier: Programming Language :: Python :: 3.12
Classifier: Programming Language :: Python :: 3.13
Classifier: Topic :: Software Development :: Libraries :: Python Modules
Requires-Dist: aiohttp (>=3.0.0)
Requires-Dist: awesomeversion (>=22.1.0)
Requires-Dist: backoff (>=2.2.0)
Requires-Dist: cachetools (>=4.0.0)
Requires-Dist: yarl (>=1.6.0)
Project-URL: Bug Tracker, https://github.com/Moustachauve/pytechnove/issues
Project-URL: Changelog, https://github.com/Moustachauve/pytechnove/releases
Project-URL: Documentation, https://github.com/Moustachauve/pytechnove
Project-URL: Homepage, https://github.com/Moustachauve/pytechnove
Project-URL: Repository, https://github.com/Moustachauve/pytechnove
